imperix/NodeLink.py
imperix/__init__.py
imperix/connection.py
imperix/protocol/__init__.py
imperix/protocol/auth.py
imperix/protocol/control.py
imperix/protocol/data.py
imperix/protocol/image.py
imperix/protocol/mission.py
imperix/protocol/packet.py
imperix/protocol/request.py
imperix/protocol/telemetry.py
imperix/protocol/video.py
imperix-0.2.5.dist-info/LICENSE.txt
imperix-0.2.5.dist-info/METADATA
imperix-0.2.5.dist-info/WHEEL
imperix-0.2.5.dist-info/top_level.txt
imperix-0.2.5.dist-info/RECORD
