Metadata-Version: 2.1
Name: imperix
Version: 0.2.5
Summary: Imperix Node SDK including the NodeLink communication handlers that allow robots and drones to communicate with the Imperix streamers and Commander API.
Home-page: https://bitbucket.org/pinetree-ai/imperix-node-sdk-python3
Author: Aptus Engineering Inc.
Author-email: software@aptusai.com
License: UNKNOWN
Platform: UNKNOWN
Classifier: Programming Language :: Python :: 3
Classifier: License :: OSI Approved :: MIT License
Classifier: Operating System :: OS Independent
Requires-Python: >=3.6
Requires-Dist: Pillow
Requires-Dist: asyncio
Requires-Dist: numpy
Requires-Dist: requests
Requires-Dist: websockets
